modelclone/__init__.py
modelclone/admin.py
modelclone/models.py
modelclone/urls.py
modelclone/views.py
modelclone/templates/modelclone/change_form.html
django_modelclone_next-0.8.2.dist-info/LICENSE
django_modelclone_next-0.8.2.dist-info/METADATA
django_modelclone_next-0.8.2.dist-info/WHEEL
django_modelclone_next-0.8.2.dist-info/top_level.txt
django_modelclone_next-0.8.2.dist-info/RECORD
